tgscheduler/scheduler.py
tgscheduler/__init__.py
tgscheduler/kronos.py
tgscheduler/tests/__init__.py
tgscheduler/tests/test_scheduler.py
TGScheduler-1.7.0.dist-info/metadata.json
TGScheduler-1.7.0.dist-info/METADATA
TGScheduler-1.7.0.dist-info/WHEEL
TGScheduler-1.7.0.dist-info/top_level.txt
TGScheduler-1.7.0.dist-info/DESCRIPTION.rst
TGScheduler-1.7.0.dist-info/RECORD
