Metadata-Version: 1.1
Name: TGScheduler
Version: 1.7.0
Summary: Pure Python Scheduler
Home-page: https://bitbucket.org/xcg/tgscheduler
Author: Vince Spicer
Author-email: vinces1979@gmail.com
License: MIT
Keywords: turbogears tg tg2 scheduler
Platform: UNKNOWN
Classifier: Development Status :: 5 - Production/Stable
Classifier: Operating System :: OS Independent
Classifier: Programming Language :: Python
Classifier: License :: OSI Approved :: MIT License
Classifier: Topic :: Software Development :: Libraries :: Python Modules
